{
  "$schema": "http://json-schema.org/draft-07/schema#",
  "$id": "https://weavster.dev/schemas/flow.schema.json",
  "title": "Weavster flow",
  "description": "Schema for a Weavster flow file: an ordered list of transform steps.",
  "type": "object",
  "required": ["steps"],
  "additionalProperties": false,
  "properties": {
    "steps": {
      "description": "Transform steps, run in order as a mutate-in-place pipeline.",
      "type": "array",
      "items": { "$ref": "#/$defs/step" }
    }
  },
  "$defs": {
    "path": {
      "description": "A dotted/bracketed path into the canonical model, e.g. order.line[0].sku.",
      "type": "string",
      "minLength": 1
    },
    "step": {
      "type": "object",
      "required": ["op"],
      "oneOf": [
        {
          "description": "Copy the value at `from` to `to`.",
          "additionalProperties": false,
          "required": ["op", "from", "to"],
          "properties": {
            "op": { "const": "map" },
            "from": { "$ref": "#/$defs/path" },
            "to": { "$ref": "#/$defs/path" }
          }
        },
        {
          "description": "Move the value at `from` to `to`.",
          "additionalProperties": false,
          "required": ["op", "from", "to"],
          "properties": {
            "op": { "const": "rename" },
            "from": { "$ref": "#/$defs/path" },
            "to": { "$ref": "#/$defs/path" }
          }
        },
        {
          "description": "Set `at` to `value` only when nothing is there yet.",
          "additionalProperties": false,
          "required": ["op", "at", "value"],
          "properties": {
            "op": { "const": "default" },
            "at": { "$ref": "#/$defs/path" },
            "value": {}
          }
        },
        {
          "description": "Join `parts` (each a path or literal value) into a string at `to`.",
          "additionalProperties": false,
          "required": ["op", "to", "parts"],
          "properties": {
            "op": { "const": "concat" },
            "to": { "$ref": "#/$defs/path" },
            "sep": { "type": "string" },
            "parts": {
              "type": "array",
              "items": {
                "type": "object",
                "additionalProperties": false,
                "properties": {
                  "path": { "$ref": "#/$defs/path" },
                  "value": {}
                },
                "oneOf": [{ "required": ["path"] }, { "required": ["value"] }]
              }
            }
          }
        },
        {
          "description": "Apply a string function from `from` to `to` (default `from`).",
          "additionalProperties": false,
          "required": ["op", "fn", "from"],
          "properties": {
            "op": { "const": "str" },
            "fn": { "enum": ["upper", "lower", "trim"] },
            "from": { "$ref": "#/$defs/path" },
            "to": { "$ref": "#/$defs/path" }
          }
        },
        {
          "description": "Apply a date function from `from` to `to` (default `from`).",
          "additionalProperties": false,
          "required": ["op", "fn", "from"],
          "properties": {
            "op": { "const": "date" },
            "fn": { "enum": ["toIso"] },
            "from": { "$ref": "#/$defs/path" },
            "to": { "$ref": "#/$defs/path" }
          }
        }
      ]
    }
  }
}
